{
  "hash": "9bb0b7044c41cba75188dee0b69d9328",
  "result": {
    "engine": "knitr",
    "markdown": "---\ntitle: развитие\n---\n\n\n\n[![](images/wiktionary.png 'смотреть в словаре Wiktionary'){height=7mm}](https://ru.wiktionary.org/wiki/развитие)\n[![](images/ruscorpora.png 'смотреть в Национальном корпусе Русского языка'){height=7mm}](https://ruscorpora.ru/word/main?req=развитие)\n\n\n\n\n\n<details>\n<summary>парадигма</summary>\n<table class=\"morfotable ru\" style=\"clear:right; margin-left:0.5em; margin-bottom:0.5em; border: 1px solid #6699CC; border-collapse:collapse; max-width:100% !important; display:block; overflow-x:auto\" cellpadding=\"3\" rules=\"all\"><tbody>\n<tr>\n<th bgcolor=\"#eef9ff\">\nпадеж\n</th>\n<th bgcolor=\"#eef9ff\">\nед. ч.\n</th>\n<th bgcolor=\"#eef9ff\">\nмн. ч.\n</th>\n</tr>\n<tr>\n<td bgcolor=\"#eef9ff\">\nИм.\n</td>\n<td bgcolor=\"#ffffff\">разви́тие\n</td>\n<td bgcolor=\"#ffffff\">разви́тия\n</td>\n</tr>\n<tr>\n<td bgcolor=\"#eef9ff\">\nР.\n</td>\n<td bgcolor=\"#ffffff\">разви́тия\n</td>\n<td bgcolor=\"#ffffff\">разви́тий\n</td>\n</tr>\n<tr>\n<td bgcolor=\"#eef9ff\">\nД.\n</td>\n<td bgcolor=\"#ffffff\">разви́тию\n</td>\n<td bgcolor=\"#ffffff\">разви́тиям\n</td>\n</tr>\n<tr>\n<td bgcolor=\"#eef9ff\">\nВ.\n</td>\n<td bgcolor=\"#ffffff\">разви́тие\n</td>\n<td bgcolor=\"#ffffff\">разви́тия\n</td>\n</tr>\n<tr>\n<td bgcolor=\"#eef9ff\">\nТв.\n</td>\n<td bgcolor=\"#ffffff\">разви́тием\n</td>\n<td bgcolor=\"#ffffff\">разви́тиями\n</td>\n</tr>\n<tr>\n<td bgcolor=\"#eef9ff\">\nПр.\n</td>\n<td bgcolor=\"#ffffff\">разви́тии\n</td>\n<td bgcolor=\"#ffffff\">разви́тиях\n</td>\n</tr>\n</tbody></table>\n\n</details>\n\n\n::: {.panel-tabset}\n\n## конструкции\n\n\n\n::: {.cell}\n::: {.cell-output-display}\n\n```{=html}\n<div class=\"datatables html-widget html-fill-item\" id=\"htmlwidget-fc11038dddc8b78862db\" style=\"width:100%;height:auto;\"></div>\n<script type=\"application/json\" data-for=\"htmlwidget-fc11038dddc8b78862db\">{\"x\":{\"filter\":\"top\",\"vertical\":false,\"filterHTML\":\"<tr>\\n  <td data-type=\\\"character\\\" style=\\\"vertical-align: top;\\\">\\n    <div class=\\\"form-group has-feedback\\\" style=\\\"margin-bottom: auto;\\\">\\n      <input type=\\\"search\\\" placeholder=\\\"All\\\" class=\\\"form-control\\\" style=\\\"width: 100%;\\\"/>\\n      <span class=\\\"glyphicon glyphicon-remove-circle form-control-feedback\\\"><\\/span>\\n    <\\/div>\\n  <\\/td>\\n  <td data-type=\\\"character\\\" style=\\\"vertical-align: top;\\\">\\n    <div class=\\\"form-group has-feedback\\\" style=\\\"margin-bottom: auto;\\\">\\n      <input type=\\\"search\\\" placeholder=\\\"All\\\" class=\\\"form-control\\\" style=\\\"width: 100%;\\\"/>\\n      <span class=\\\"glyphicon glyphicon-remove-circle form-control-feedback\\\"><\\/span>\\n    <\\/div>\\n  <\\/td>\\n<\\/tr>\",\"data\":[[\"вклад в развитие\",\"влияние на развитие\",\"вложение в развитие\",\"воздействие на развитие\",\"инвестиции в развитие\",\"индекс развития\",\"критерий развития\",\"модель развития\",\"перспективы развития\",\"по мере развития\",\"поддержание и развитие\",\"показатели развития\",\"получить развитие\",\"потенциал развития\",\"предпосылки для развития\",\"проекты по развитию\",\"развитие инноваций\",\"развитие инфраструктуры\",\"развитие производительных сил\",\"развитие рынка\",\"развитие экономики\",\"расходы на развитие\",\"региональное развитие\",\"роль в развитии\",\"создание и развитие\",\"социально-экономическое развитие\",\"социальное развитие\",\"способствовать развитию\",\"становление и развитие\",\"стратегическое развитие\",\"стратегия развития\",\"темпы развития\",\"технологическое развитие\",\"толчок к развитию\",\"управление развитием\",\"уровень развития\",\"условия для развития\",\"устойчивое развитие\",\"формирование и развитие\",\"функционирование и развитие чего?\",\"экономическое развитие\",\"этап развития\"],[\"• Восточная Азия вносит большой вклад в развитие мировой экономики.\",\"• Финансовая помощь международных организаций не оказывает влияния на развитие экономики страны.\",\"• Вложение в развитие технологий дает возможность получить прибыль в перспективе.\",\"• Пространственные эффекты оказывают сильное воздействие на развитие регионов.\",\"• Инвестиции в развитие экономики и социальной сферы региона за год сократились на 7,6%.\",\"• индекс развития человеческого потенциала\",\"• Выделяют целевые критерии развития национальной финансовой системы.\",\"• трансформация модели развития<br>• модель экономического развития\",\"• В статье описаны тенденции и перспективы развития регулирования в банковской сфере.\",\"• По мере развития и роста благосостояния стран в их экономике увеличивается доля сектора услуг.\",\"• Большую часть средств предполагается потратить на поддержание и развитие инфраструктуры.\",\"• основные показатели развития<br>• показатели социальноэкономического развития\",\"• В мире получило развитие новое явление – децентрализованные финансы Decentralized Finance, DeFi).\",\"• Шкала индекса – от 0 до 1, где 1 означает достижение максимального потенциала развития человеческого капитала.\",\"• Развитие инфраструктуры создает предпосылки для развития сектора производства товарной продукции.\",\"• Региональные проекты по развитию цифровой экономики утверждены во всех субъектах РФ.\",\"• развитие социальных инноваций\",\"• развитие транспортной инфраструктуры<br>• развитие социальной инфраструктуры\",\"• Развитие производительных сил выступает в качестве критерия экономического прогресса.\",\"• развитие внутреннего рынка\",\"• развитие рыночной экономики\",\"• Расходы на развитие авиационной промышленности могут вырасти на 4,6 млрд руб.\",\"• проблемы регионального развития<br>• управление региональным развитием\",\"• Малые города играют значимую роль в развитии экономики государства.\",\"• Меры направлены на снижение барьеров для создания и развития бизнеса.\",\"• стратегии социально-экономического развития<br>• социально-экономическое развитие региона<br>• долгосрочное социально-экономическое развитие<br>• теория социально-экономического развития\",\"• концепция устойчивого развития\",\"• Какой уровень цен на нефть будет способствовать развитию экономики России?\",\"• Рассмотрены основные этапы становления и развития экономической теории.\",\"• стратегическое развитие страны\",\"• стратегия регионального развития<br>• государственная стратегия развития<br>• разработка стратегии развития<br>• утверждение стратегии развития\",\"• высокие темпы развития\",\"• Двигателем экономического роста и доходов в долгосрочной перспективе становится технологическое развитие.\",\"• Новые законы по поддержке бизнеса дадут толчок к развитию экономики.\",\"• управление развитием территории\",\"• высокий уровень развития<br>• уровень инновационного развития<br>• влияние уровня развития<br>• по уровню развития\",\"• Финансовые условия для развитых экономик в последние месяцы улучшились.\",\"• обеспечение устойчивого развития<br>• стратегия пространственного развития<br>• экономика устойчивого развития\",\"• Происходит формирование и развитие глобального рынка систем и технологий ИИ.\",\"• В статье собраны актуальные проблемы функционирования и развития энергетических и сырьевых рынков.\",\"• уровень экономического развития<br>• экономическое развитие региона<br>• темпы экономического развития\",\"• современный этап развития\"]],\"container\":\"<table class=\\\"display\\\">\\n  <thead>\\n    <tr>\\n      <th>выражение<\\/th>\\n      <th>пример<\\/th>\\n    <\\/tr>\\n  <\\/thead>\\n<\\/table>\",\"options\":{\"pageLength\":15,\"dom\":\"tp\",\"columnDefs\":[{\"name\":\"выражение\",\"targets\":0},{\"name\":\"пример\",\"targets\":1}],\"order\":[],\"autoWidth\":false,\"orderClasses\":false,\"orderCellsTop\":true,\"lengthMenu\":[10,15,25,50,100]}},\"evals\":[],\"jsHooks\":[]}</script>\n```\n\n:::\n:::\n\n\n\n## упражнения\n\n\n\n\n\n::: {.cell}\n::: {.cell-output-display}\n\n```{=html}\n<form name=\"form_93895\" onsubmit=\"return validate_form_93895()\" method=\"post\">\n<fieldset>\n<legend><h4 id=\"section\">Поставьте слова в правильном порядке:</h4></legend>\n<table data-quarto-disable-processing=\"true\">\n<tr id=\"task_93895\">\n<td id=\"answer_93895_4\" style=\"padding:5px; border:1px solid #ccc;\">потенциала</td>\n<td style=\"padding:5px\">\n<button type=\"button\" onclick=\"swapElementsH(this);\">⇆</button>\n</td>\n<td id=\"answer_93895_3\" style=\"padding:5px; border:1px solid #ccc;\">человеческого</td>\n<td style=\"padding:5px\">\n<button type=\"button\" onclick=\"swapElementsH(this);\">⇆</button>\n</td>\n<td id=\"answer_93895_1\" style=\"padding:5px; border:1px solid #ccc;\">индекс</td>\n<td style=\"padding:5px\">\n<button type=\"button\" onclick=\"swapElementsH(this);\">⇆</button>\n</td>\n<td id=\"answer_93895_2\" style=\"padding:5px; border:1px solid #ccc;\">развития</td>\n</tr>\n</table>\n<input type=\"submit\" value=\"проверить\"/>\n<div id=\"result_93895\"></div>\n</fieldset>\n</form>\n<script>function validate_form_93895() {var text;var ch = document.getElementById('task_93895').children; if(ch[0].id == 'answer_93895_1'&ch[2].id == 'answer_93895_2'&ch[4].id == 'answer_93895_3'&ch[6].id == 'answer_93895_4'){text = 'все верно!';} else {text = 'к сожалению нет, попробуйте еще раз…';} document.getElementById('result_93895').innerHTML = text; evaluate_final_score(); return false;}function swapElementsH(element) {const parent = element.parentNode; const afterNode = parent.nextElementSibling; const beforeNode = parent.previousElementSibling; parent.insertAdjacentElement('beforebegin', afterNode); parent.insertAdjacentElement('afterend', beforeNode);}function evaluate_final_score(){\n         element = document.getElementById('checkdown_final_score');\n         if(element === null){return false;} else {var element, text, res1;res1 = document.getElementById('result_93895').innerText == 'все верно!';text = res1;element.innerHTML = text;\n         return false;\n         }}</script>\n```\n\n:::\n\n::: {.cell-output-display}\n\n```{=html}\n<div id=\"hint_96662\" onclick=\"return show_hint_96662()\">🔎 Нажмите, чтобы посмотреть ответ</div>\n<div id=\"result_96662\" onclick=\"return show_hint_96662()\"></div>\n<script>function show_hint_96662(){var x = document.getElementById('result_96662').innerHTML; if(!x){document.getElementById('result_96662').innerHTML = 'индекс; развития; человеческого; потенциала';} else {document.getElementById('result_96662').innerHTML = '';}}</script>\n```\n\n:::\n:::\n\n::: {.cell}\n::: {.cell-output-display}\n\n```{=html}\n<form name=\"form_94714\" onsubmit=\"return validate_form_94714()\" method=\"post\">\n<fieldset>\n<legend><h4 id=\"section\">Поставьте фрагменты предложений в правильном порядке:</h4></legend>\n<table data-quarto-disable-processing=\"true\">\n<tbody id=\"task_94714\">\n<tr>\n<td id=\"answer_94714_1\" style=\"padding:5px; border:1px solid #ccc;\">взаимосвязь нормальной</td>\n</tr>\n<tr>\n<td style=\"padding:5px\">\n<button type=\"button\" onclick=\"swapElementsV(this);\">⇅</button>\n</td>\n</tr>\n<tr>\n<td id=\"answer_94714_3\" style=\"padding:5px; border:1px solid #ccc;\">дифференциации доходов</td>\n</tr>\n<tr>\n<td style=\"padding:5px\">\n<button type=\"button\" onclick=\"swapElementsV(this);\">⇅</button>\n</td>\n</tr>\n<tr>\n<td id=\"answer_94714_4\" style=\"padding:5px; border:1px solid #ccc;\">населения с показателями развития региональных экономик</td>\n</tr>\n<tr>\n<td style=\"padding:5px\">\n<button type=\"button\" onclick=\"swapElementsV(this);\">⇅</button>\n</td>\n</tr>\n<tr>\n<td id=\"answer_94714_2\" style=\"padding:5px; border:1px solid #ccc;\">и избыточной</td>\n</tr>\n</tbody>\n</table>\n<input type=\"submit\" value=\"проверить\"/>\n<div id=\"result_94714\"></div>\n</fieldset>\n</form>\n<script>function validate_form_94714() {var text;var ch = document.getElementById('task_94714').children; if(ch[0].children[0].id == 'answer_94714_1'&ch[2].children[0].id == 'answer_94714_2'&ch[4].children[0].id == 'answer_94714_3'&ch[6].children[0].id == 'answer_94714_4'){text = 'все верно!';} else {text = 'к сожалению нет, попробуйте еще раз…';} document.getElementById('result_94714').innerHTML = text; evaluate_final_score(); return false;}function swapElementsV(element) {const parent = element.parentNode.parentNode; const afterNode = parent.nextElementSibling; const beforeNode = parent.previousElementSibling; parent.insertAdjacentElement('beforebegin', afterNode); parent.insertAdjacentElement('afterend', beforeNode);}function evaluate_final_score(){\n         element = document.getElementById('checkdown_final_score');\n         if(element === null){return false;} else {var element, text, res1, res2;res1 = document.getElementById('result_93895').innerText == 'все верно!'; res2 = document.getElementById('result_94714').innerText == 'все верно!';text = res1 + res2;element.innerHTML = text;\n         return false;\n         }}</script>\n```\n\n:::\n\n::: {.cell-output-display}\n\n```{=html}\n<div id=\"hint_82296\" onclick=\"return show_hint_82296()\">🔎 Нажмите, чтобы посмотреть ответ</div>\n<div id=\"result_82296\" onclick=\"return show_hint_82296()\"></div>\n<script>function show_hint_82296(){var x = document.getElementById('result_82296').innerHTML; if(!x){document.getElementById('result_82296').innerHTML = 'взаимосвязь нормальной; и избыточной; дифференциации доходов; населения с показателями развития региональных экономик';} else {document.getElementById('result_82296').innerHTML = '';}}</script>\n```\n\n:::\n:::\n\n::: {.cell}\n::: {.cell-output-display}\n\n```{=html}\n<form name=\"form_91824\" onsubmit=\"return validate_form_91824()\" method=\"post\">\n<fieldset>\n<legend><h4 id=\"section\">Поставьте фрагменты предложений в правильном порядке:</h4></legend>\n<table data-quarto-disable-processing=\"true\">\n<tbody id=\"task_91824\">\n<tr>\n<td id=\"answer_91824_2\" style=\"padding:5px; border:1px solid #ccc;\">реформирования отечественных субъектов</td>\n</tr>\n<tr>\n<td style=\"padding:5px\">\n<button type=\"button\" onclick=\"swapElementsV(this);\">⇅</button>\n</td>\n</tr>\n<tr>\n<td id=\"answer_91824_4\" style=\"padding:5px; border:1px solid #ccc;\">и развитие корпоративной формы собственности</td>\n</tr>\n<tr>\n<td style=\"padding:5px\">\n<button type=\"button\" onclick=\"swapElementsV(this);\">⇅</button>\n</td>\n</tr>\n<tr>\n<td id=\"answer_91824_3\" style=\"padding:5px; border:1px solid #ccc;\">хозяйствования становится создание</td>\n</tr>\n<tr>\n<td style=\"padding:5px\">\n<button type=\"button\" onclick=\"swapElementsV(this);\">⇅</button>\n</td>\n</tr>\n<tr>\n<td id=\"answer_91824_1\" style=\"padding:5px; border:1px solid #ccc;\">одним из направлений</td>\n</tr>\n</tbody>\n</table>\n<input type=\"submit\" value=\"проверить\"/>\n<div id=\"result_91824\"></div>\n</fieldset>\n</form>\n<script>function validate_form_91824() {var text;var ch = document.getElementById('task_91824').children; if(ch[0].children[0].id == 'answer_91824_1'&ch[2].children[0].id == 'answer_91824_2'&ch[4].children[0].id == 'answer_91824_3'&ch[6].children[0].id == 'answer_91824_4'){text = 'все верно!';} else {text = 'к сожалению нет, попробуйте еще раз…';} document.getElementById('result_91824').innerHTML = text; evaluate_final_score(); return false;}function swapElementsV(element) {const parent = element.parentNode.parentNode; const afterNode = parent.nextElementSibling; const beforeNode = parent.previousElementSibling; parent.insertAdjacentElement('beforebegin', afterNode); parent.insertAdjacentElement('afterend', beforeNode);}function evaluate_final_score(){\n         element = document.getElementById('checkdown_final_score');\n         if(element === null){return false;} else {var element, text, res1, res2, res3;res1 = document.getElementById('result_93895').innerText == 'все верно!'; res2 = document.getElementById('result_94714').innerText == 'все верно!'; res3 = document.getElementById('result_91824').innerText == 'все верно!';text = res1 + res2 + res3;element.innerHTML = text;\n         return false;\n         }}</script>\n```\n\n:::\n\n::: {.cell-output-display}\n\n```{=html}\n<div id=\"hint_11919\" onclick=\"return show_hint_11919()\">🔎 Нажмите, чтобы посмотреть ответ</div>\n<div id=\"result_11919\" onclick=\"return show_hint_11919()\"></div>\n<script>function show_hint_11919(){var x = document.getElementById('result_11919').innerHTML; if(!x){document.getElementById('result_11919').innerHTML = 'одним из направлений; реформирования отечественных субъектов; хозяйствования становится создание; и развитие корпоративной формы собственности';} else {document.getElementById('result_11919').innerHTML = '';}}</script>\n```\n\n:::\n:::\n\n::: {.cell}\n::: {.cell-output-display}\n\n```{=html}\n<form name=\"form_41432\" onsubmit=\"return validate_form_41432()\" method=\"post\">\n<fieldset>\n<legend><h4 id=\"section\">Поставьте фрагменты предложений в правильном порядке:</h4></legend>\n<table data-quarto-disable-processing=\"true\">\n<tbody id=\"task_41432\">\n<tr>\n<td id=\"answer_41432_3\" style=\"padding:5px; border:1px solid #ccc;\">здравоохранение, культуру не</td>\n</tr>\n<tr>\n<td style=\"padding:5px\">\n<button type=\"button\" onclick=\"swapElementsV(this);\">⇅</button>\n</td>\n</tr>\n<tr>\n<td id=\"answer_41432_1\" style=\"padding:5px; border:1px solid #ccc;\">государственные расходы на</td>\n</tr>\n<tr>\n<td style=\"padding:5px\">\n<button type=\"button\" onclick=\"swapElementsV(this);\">⇅</button>\n</td>\n</tr>\n<tr>\n<td id=\"answer_41432_4\" style=\"padding:5px; border:1px solid #ccc;\">компенсируют недостаток индивидуальных вложений</td>\n</tr>\n<tr>\n<td style=\"padding:5px\">\n<button type=\"button\" onclick=\"swapElementsV(this);\">⇅</button>\n</td>\n</tr>\n<tr>\n<td id=\"answer_41432_2\" style=\"padding:5px; border:1px solid #ccc;\">развитие системы образования,</td>\n</tr>\n</tbody>\n</table>\n<input type=\"submit\" value=\"проверить\"/>\n<div id=\"result_41432\"></div>\n</fieldset>\n</form>\n<script>function validate_form_41432() {var text;var ch = document.getElementById('task_41432').children; if(ch[0].children[0].id == 'answer_41432_1'&ch[2].children[0].id == 'answer_41432_2'&ch[4].children[0].id == 'answer_41432_3'&ch[6].children[0].id == 'answer_41432_4'){text = 'все верно!';} else {text = 'к сожалению нет, попробуйте еще раз…';} document.getElementById('result_41432').innerHTML = text; evaluate_final_score(); return false;}function swapElementsV(element) {const parent = element.parentNode.parentNode; const afterNode = parent.nextElementSibling; const beforeNode = parent.previousElementSibling; parent.insertAdjacentElement('beforebegin', afterNode); parent.insertAdjacentElement('afterend', beforeNode);}function evaluate_final_score(){\n         element = document.getElementById('checkdown_final_score');\n         if(element === null){return false;} else {var element, text, res1, res2, res3, res4;res1 = document.getElementById('result_93895').innerText == 'все верно!'; res2 = document.getElementById('result_94714').innerText == 'все верно!'; res3 = document.getElementById('result_91824').innerText == 'все верно!'; res4 = document.getElementById('result_41432').innerText == 'все верно!';text = res1 + res2 + res3 + res4;element.innerHTML = text;\n         return false;\n         }}</script>\n```\n\n:::\n\n::: {.cell-output-display}\n\n```{=html}\n<div id=\"hint_34221\" onclick=\"return show_hint_34221()\">🔎 Нажмите, чтобы посмотреть ответ</div>\n<div id=\"result_34221\" onclick=\"return show_hint_34221()\"></div>\n<script>function show_hint_34221(){var x = document.getElementById('result_34221').innerHTML; if(!x){document.getElementById('result_34221').innerHTML = 'государственные расходы на; развитие системы образования,; здравоохранение, культуру не; компенсируют недостаток индивидуальных вложений';} else {document.getElementById('result_34221').innerHTML = '';}}</script>\n```\n\n:::\n:::\n\n::: {.cell}\n::: {.cell-output-display}\n\n```{=html}\n<form name=\"form_86938\" onsubmit=\"return validate_form_86938()\" method=\"post\">\n<fieldset>\n<legend><h4 id=\"section\">Поставьте фрагменты предложений в правильном порядке:</h4></legend>\n<table data-quarto-disable-processing=\"true\">\n<tbody id=\"task_86938\">\n<tr>\n<td id=\"answer_86938_2\" style=\"padding:5px; border:1px solid #ccc;\">– один из</td>\n</tr>\n<tr>\n<td style=\"padding:5px\">\n<button type=\"button\" onclick=\"swapElementsV(this);\">⇅</button>\n</td>\n</tr>\n<tr>\n<td id=\"answer_86938_1\" style=\"padding:5px; border:1px solid #ccc;\">состояние внешнеторговых связей</td>\n</tr>\n<tr>\n<td style=\"padding:5px\">\n<button type=\"button\" onclick=\"swapElementsV(this);\">⇅</button>\n</td>\n</tr>\n<tr>\n<td id=\"answer_86938_3\" style=\"padding:5px; border:1px solid #ccc;\">важнейших показателей развития</td>\n</tr>\n<tr>\n<td style=\"padding:5px\">\n<button type=\"button\" onclick=\"swapElementsV(this);\">⇅</button>\n</td>\n</tr>\n<tr>\n<td id=\"answer_86938_4\" style=\"padding:5px; border:1px solid #ccc;\">интеграционных процессов на территории Евразийского экономического союза</td>\n</tr>\n</tbody>\n</table>\n<input type=\"submit\" value=\"проверить\"/>\n<div id=\"result_86938\"></div>\n</fieldset>\n</form>\n<script>function validate_form_86938() {var text;var ch = document.getElementById('task_86938').children; if(ch[0].children[0].id == 'answer_86938_1'&ch[2].children[0].id == 'answer_86938_2'&ch[4].children[0].id == 'answer_86938_3'&ch[6].children[0].id == 'answer_86938_4'){text = 'все верно!';} else {text = 'к сожалению нет, попробуйте еще раз…';} document.getElementById('result_86938').innerHTML = text; evaluate_final_score(); return false;}function swapElementsV(element) {const parent = element.parentNode.parentNode; const afterNode = parent.nextElementSibling; const beforeNode = parent.previousElementSibling; parent.insertAdjacentElement('beforebegin', afterNode); parent.insertAdjacentElement('afterend', beforeNode);}function evaluate_final_score(){\n         element = document.getElementById('checkdown_final_score');\n         if(element === null){return false;} else {var element, text, res1, res2, res3, res4, res5;res1 = document.getElementById('result_93895').innerText == 'все верно!'; res2 = document.getElementById('result_94714').innerText == 'все верно!'; res3 = document.getElementById('result_91824').innerText == 'все верно!'; res4 = document.getElementById('result_41432').innerText == 'все верно!'; res5 = document.getElementById('result_86938').innerText == 'все верно!';text = res1 + res2 + res3 + res4 + res5;element.innerHTML = text;\n         return false;\n         }}</script>\n```\n\n:::\n\n::: {.cell-output-display}\n\n```{=html}\n<div id=\"hint_30149\" onclick=\"return show_hint_30149()\">🔎 Нажмите, чтобы посмотреть ответ</div>\n<div id=\"result_30149\" onclick=\"return show_hint_30149()\"></div>\n<script>function show_hint_30149(){var x = document.getElementById('result_30149').innerHTML; if(!x){document.getElementById('result_30149').innerHTML = 'состояние внешнеторговых связей; – один из; важнейших показателей развития; интеграционных процессов на территории Евразийского экономического союза';} else {document.getElementById('result_30149').innerHTML = '';}}</script>\n```\n\n:::\n:::\n\n::: {.cell}\n::: {.cell-output-display}\n\n```{=html}\n<form name=\"form_52218\" onsubmit=\"return validate_form_52218()\" method=\"post\">\n<fieldset>\n<legend><h4 id=\"section\">Поставьте фрагменты предложений в правильном порядке:</h4></legend>\n<table data-quarto-disable-processing=\"true\">\n<tbody id=\"task_52218\">\n<tr>\n<td id=\"answer_52218_3\" style=\"padding:5px; border:1px solid #ccc;\">связаны с освоением новых</td>\n</tr>\n<tr>\n<td style=\"padding:5px\">\n<button type=\"button\" onclick=\"swapElementsV(this);\">⇅</button>\n</td>\n</tr>\n<tr>\n<td id=\"answer_52218_4\" style=\"padding:5px; border:1px solid #ccc;\">месторождений особо ценного минерального сырья</td>\n</tr>\n<tr>\n<td style=\"padding:5px\">\n<button type=\"button\" onclick=\"swapElementsV(this);\">⇅</button>\n</td>\n</tr>\n<tr>\n<td id=\"answer_52218_2\" style=\"padding:5px; border:1px solid #ccc;\">в зоне Крайнего Севера</td>\n</tr>\n<tr>\n<td style=\"padding:5px\">\n<button type=\"button\" onclick=\"swapElementsV(this);\">⇅</button>\n</td>\n</tr>\n<tr>\n<td id=\"answer_52218_1\" style=\"padding:5px; border:1px solid #ccc;\">ближайшие перспективы развития экономики</td>\n</tr>\n</tbody>\n</table>\n<input type=\"submit\" value=\"проверить\"/>\n<div id=\"result_52218\"></div>\n</fieldset>\n</form>\n<script>function validate_form_52218() {var text;var ch = document.getElementById('task_52218').children; if(ch[0].children[0].id == 'answer_52218_1'&ch[2].children[0].id == 'answer_52218_2'&ch[4].children[0].id == 'answer_52218_3'&ch[6].children[0].id == 'answer_52218_4'){text = 'все верно!';} else {text = 'к сожалению нет, попробуйте еще раз…';} document.getElementById('result_52218').innerHTML = text; evaluate_final_score(); return false;}function swapElementsV(element) {const parent = element.parentNode.parentNode; const afterNode = parent.nextElementSibling; const beforeNode = parent.previousElementSibling; parent.insertAdjacentElement('beforebegin', afterNode); parent.insertAdjacentElement('afterend', beforeNode);}function evaluate_final_score(){\n         element = document.getElementById('checkdown_final_score');\n         if(element === null){return false;} else {var element, text, res1, res2, res3, res4, res5, res6;res1 = document.getElementById('result_93895').innerText == 'все верно!'; res2 = document.getElementById('result_94714').innerText == 'все верно!'; res3 = document.getElementById('result_91824').innerText == 'все верно!'; res4 = document.getElementById('result_41432').innerText == 'все верно!'; res5 = document.getElementById('result_86938').innerText == 'все верно!'; res6 = document.getElementById('result_52218').innerText == 'все верно!';text = res1 + res2 + res3 + res4 + res5 + res6;element.innerHTML = text;\n         return false;\n         }}</script>\n```\n\n:::\n\n::: {.cell-output-display}\n\n```{=html}\n<div id=\"hint_90571\" onclick=\"return show_hint_90571()\">🔎 Нажмите, чтобы посмотреть ответ</div>\n<div id=\"result_90571\" onclick=\"return show_hint_90571()\"></div>\n<script>function show_hint_90571(){var x = document.getElementById('result_90571').innerHTML; if(!x){document.getElementById('result_90571').innerHTML = 'ближайшие перспективы развития экономики; в зоне Крайнего Севера; связаны с освоением новых; месторождений особо ценного минерального сырья';} else {document.getElementById('result_90571').innerHTML = '';}}</script>\n```\n\n:::\n:::\n\n::: {.cell}\n::: {.cell-output-display}\n\n```{=html}\n<form name=\"form_51187\" onsubmit=\"return validate_form_51187()\" method=\"post\">\n<fieldset>\n<legend><h4 id=\"15-22\">В промышленно развитых странах для поддержания социальной безопасности перераспределяется 15—22% ВВП, что создает ____________ (<strong>предпосылка, для, развитие</strong>) человека. Основное место в этих расходах занимает социальное обеспечение.</h4></legend>\n<input type=\"text\" placeholder=\"\" name=\"answer_51187\"/>\n<input type=\"submit\" value=\"проверить\"/>\n<div id=\"result_51187\"></div>\n</fieldset>\n</form>\n<script>function validate_form_51187() {var x, text; var x = document.forms['form_51187']['answer_51187'].value;if (x == 'предпосылки для развития'){text = 'все верно!';} else {text = 'к сожалению нет, попробуйте еще раз…';} document.getElementById('result_51187').innerHTML = text; evaluate_final_score(); return false;}function evaluate_final_score(){\n         element = document.getElementById('checkdown_final_score');\n         if(element === null){return false;} else {var element, text, res1, res2, res3, res4, res5, res6, res7;res1 = document.getElementById('result_93895').innerText == 'все верно!'; res2 = document.getElementById('result_94714').innerText == 'все верно!'; res3 = document.getElementById('result_91824').innerText == 'все верно!'; res4 = document.getElementById('result_41432').innerText == 'все верно!'; res5 = document.getElementById('result_86938').innerText == 'все верно!'; res6 = document.getElementById('result_52218').innerText == 'все верно!'; res7 = document.getElementById('result_51187').innerText == 'все верно!';text = res1 + res2 + res3 + res4 + res5 + res6 + res7;element.innerHTML = text;\n         return false;\n         }}</script>\n```\n\n:::\n\n::: {.cell-output-display}\n\n```{=html}\n<div id=\"hint_97546\" onclick=\"return show_hint_97546()\">🔎 Нажмите, чтобы посмотреть ответ</div>\n<div id=\"result_97546\" onclick=\"return show_hint_97546()\"></div>\n<script>function show_hint_97546(){var x = document.getElementById('result_97546').innerHTML; if(!x){document.getElementById('result_97546').innerHTML = 'предпосылки для развития';} else {document.getElementById('result_97546').innerHTML = '';}}</script>\n```\n\n:::\n:::\n\n::: {.cell}\n::: {.cell-output-display}\n\n```{=html}\n<form name=\"form_13255\" onsubmit=\"return validate_form_13255()\" method=\"post\">\n<fieldset>\n<legend><h4 id=\"section\">Нормально работающие институты и инфраструктура важны для ____________ (<strong>экономический, развитие</strong>).</h4></legend>\n<input type=\"text\" placeholder=\"\" name=\"answer_13255\"/>\n<input type=\"submit\" value=\"проверить\"/>\n<div id=\"result_13255\"></div>\n</fieldset>\n</form>\n<script>function validate_form_13255() {var x, text; var x = document.forms['form_13255']['answer_13255'].value;if (x == 'экономического развития'){text = 'все верно!';} else {text = 'к сожалению нет, попробуйте еще раз…';} document.getElementById('result_13255').innerHTML = text; evaluate_final_score(); return false;}function evaluate_final_score(){\n         element = document.getElementById('checkdown_final_score');\n         if(element === null){return false;} else {var element, text, res1, res2, res3, res4, res5, res6, res7, res8;res1 = document.getElementById('result_93895').innerText == 'все верно!'; res2 = document.getElementById('result_94714').innerText == 'все верно!'; res3 = document.getElementById('result_91824').innerText == 'все верно!'; res4 = document.getElementById('result_41432').innerText == 'все верно!'; res5 = document.getElementById('result_86938').innerText == 'все верно!'; res6 = document.getElementById('result_52218').innerText == 'все верно!'; res7 = document.getElementById('result_51187').innerText == 'все верно!'; res8 = document.getElementById('result_13255').innerText == 'все верно!';text = res1 + res2 + res3 + res4 + res5 + res6 + res7 + res8;element.innerHTML = text;\n         return false;\n         }}</script>\n```\n\n:::\n\n::: {.cell-output-display}\n\n```{=html}\n<div id=\"hint_20303\" onclick=\"return show_hint_20303()\">🔎 Нажмите, чтобы посмотреть ответ</div>\n<div id=\"result_20303\" onclick=\"return show_hint_20303()\"></div>\n<script>function show_hint_20303(){var x = document.getElementById('result_20303').innerHTML; if(!x){document.getElementById('result_20303').innerHTML = 'экономического развития';} else {document.getElementById('result_20303').innerHTML = '';}}</script>\n```\n\n:::\n:::\n\n::: {.cell}\n::: {.cell-output-display}\n\n```{=html}\n<form name=\"form_38988\" onsubmit=\"return validate_form_38988()\" method=\"post\">\n<fieldset>\n<legend><h4 id=\"section\">Для ____________ (<strong>устойчивый, развитие</strong>) экономики в долгосрочной перспективе необходимо именно сотрудничество, а не только соперничество экономических субъектов.</h4></legend>\n<input type=\"text\" placeholder=\"\" name=\"answer_38988\"/>\n<input type=\"submit\" value=\"проверить\"/>\n<div id=\"result_38988\"></div>\n</fieldset>\n</form>\n<script>function validate_form_38988() {var x, text; var x = document.forms['form_38988']['answer_38988'].value;if (x == 'устойчивого развития'){text = 'все верно!';} else {text = 'к сожалению нет, попробуйте еще раз…';} document.getElementById('result_38988').innerHTML = text; evaluate_final_score(); return false;}function evaluate_final_score(){\n         element = document.getElementById('checkdown_final_score');\n         if(element === null){return false;} else {var element, text, res1, res2, res3, res4, res5, res6, res7, res8, res9;res1 = document.getElementById('result_93895').innerText == 'все верно!'; res2 = document.getElementById('result_94714').innerText == 'все верно!'; res3 = document.getElementById('result_91824').innerText == 'все верно!'; res4 = document.getElementById('result_41432').innerText == 'все верно!'; res5 = document.getElementById('result_86938').innerText == 'все верно!'; res6 = document.getElementById('result_52218').innerText == 'все верно!'; res7 = document.getElementById('result_51187').innerText == 'все верно!'; res8 = document.getElementById('result_13255').innerText == 'все верно!'; res9 = document.getElementById('result_38988').innerText == 'все верно!';text = res1 + res2 + res3 + res4 + res5 + res6 + res7 + res8 + res9;element.innerHTML = text;\n         return false;\n         }}</script>\n```\n\n:::\n\n::: {.cell-output-display}\n\n```{=html}\n<div id=\"hint_79832\" onclick=\"return show_hint_79832()\">🔎 Нажмите, чтобы посмотреть ответ</div>\n<div id=\"result_79832\" onclick=\"return show_hint_79832()\"></div>\n<script>function show_hint_79832(){var x = document.getElementById('result_79832').innerHTML; if(!x){document.getElementById('result_79832').innerHTML = 'устойчивого развития';} else {document.getElementById('result_79832').innerHTML = '';}}</script>\n```\n\n:::\n:::\n\n::: {.cell}\n::: {.cell-output-display}\n\n```{=html}\n<form name=\"form_40972\" onsubmit=\"return validate_form_40972()\" method=\"post\">\n<fieldset>\n<legend><h4 id=\"section\">Масштаб отечественных и зарубежных инвестиций в ____________ (<strong>развитие</strong>) Дальнего Востока впечатляет, однако отдача от них пока не слишком значительная.</h4></legend>\n<input type=\"text\" placeholder=\"\" name=\"answer_40972\"/>\n<input type=\"submit\" value=\"проверить\"/>\n<div id=\"result_40972\"></div>\n</fieldset>\n</form>\n<script>function validate_form_40972() {var x, text; var x = document.forms['form_40972']['answer_40972'].value;if (x == 'развитие'){text = 'все верно!';} else {text = 'к сожалению нет, попробуйте еще раз…';} document.getElementById('result_40972').innerHTML = text; evaluate_final_score(); return false;}function evaluate_final_score(){\n         element = document.getElementById('checkdown_final_score');\n         if(element === null){return false;} else {var element, text, res1, res2, res3, res4, res5, res6, res7, res8, res9, res10;res1 = document.getElementById('result_93895').innerText == 'все верно!'; res2 = document.getElementById('result_94714').innerText == 'все верно!'; res3 = document.getElementById('result_91824').innerText == 'все верно!'; res4 = document.getElementById('result_41432').innerText == 'все верно!'; res5 = document.getElementById('result_86938').innerText == 'все верно!'; res6 = document.getElementById('result_52218').innerText == 'все верно!'; res7 = document.getElementById('result_51187').innerText == 'все верно!'; res8 = document.getElementById('result_13255').innerText == 'все верно!'; res9 = document.getElementById('result_38988').innerText == 'все верно!'; res10 = document.getElementById('result_40972').innerText == 'все верно!';text = res1 + res2 + res3 + res4 + res5 + res6 + res7 + res8 + res9 + res10;element.innerHTML = text;\n         return false;\n         }}</script>\n```\n\n:::\n\n::: {.cell-output-display}\n\n```{=html}\n<div id=\"hint_91513\" onclick=\"return show_hint_91513()\">🔎 Нажмите, чтобы посмотреть ответ</div>\n<div id=\"result_91513\" onclick=\"return show_hint_91513()\"></div>\n<script>function show_hint_91513(){var x = document.getElementById('result_91513').innerHTML; if(!x){document.getElementById('result_91513').innerHTML = 'развитие';} else {document.getElementById('result_91513').innerHTML = '';}}</script>\n```\n\n:::\n:::\n\n::: {.cell}\n::: {.cell-output-display}\n\n```{=html}\n<form name=\"form_5307\" onsubmit=\"return validate_form_5307()\" method=\"post\">\n<fieldset>\n<legend><h4 id=\"section\">Взаимосвязь нормальной и избыточной дифференциации доходов населения с ____________ (<strong>показатель, развитие</strong>) региональных экономик.</h4></legend>\n<input type=\"text\" placeholder=\"\" name=\"answer_5307\"/>\n<input type=\"submit\" value=\"проверить\"/>\n<div id=\"result_5307\"></div>\n</fieldset>\n</form>\n<script>function validate_form_5307() {var x, text; var x = document.forms['form_5307']['answer_5307'].value;if (x == 'показателями развития'){text = 'все верно!';} else {text = 'к сожалению нет, попробуйте еще раз…';} document.getElementById('result_5307').innerHTML = text; evaluate_final_score(); return false;}function evaluate_final_score(){\n         element = document.getElementById('checkdown_final_score');\n         if(element === null){return false;} else {var element, text, res1, res2, res3, res4, res5, res6, res7, res8, res9, res10, res11;res1 = document.getElementById('result_93895').innerText == 'все верно!'; res2 = document.getElementById('result_94714').innerText == 'все верно!'; res3 = document.getElementById('result_91824').innerText == 'все верно!'; res4 = document.getElementById('result_41432').innerText == 'все верно!'; res5 = document.getElementById('result_86938').innerText == 'все верно!'; res6 = document.getElementById('result_52218').innerText == 'все верно!'; res7 = document.getElementById('result_51187').innerText == 'все верно!'; res8 = document.getElementById('result_13255').innerText == 'все верно!'; res9 = document.getElementById('result_38988').innerText == 'все верно!'; res10 = document.getElementById('result_40972').innerText == 'все верно!'; res11 = document.getElementById('result_5307').innerText == 'все верно!';text = res1 + res2 + res3 + res4 + res5 + res6 + res7 + res8 + res9 + res10 + res11;element.innerHTML = text;\n         return false;\n         }}</script>\n```\n\n:::\n\n::: {.cell-output-display}\n\n```{=html}\n<div id=\"hint_8799\" onclick=\"return show_hint_8799()\">🔎 Нажмите, чтобы посмотреть ответ</div>\n<div id=\"result_8799\" onclick=\"return show_hint_8799()\"></div>\n<script>function show_hint_8799(){var x = document.getElementById('result_8799').innerHTML; if(!x){document.getElementById('result_8799').innerHTML = 'показателями развития';} else {document.getElementById('result_8799').innerHTML = '';}}</script>\n```\n\n:::\n:::\n\n\n\n:::\n\n",
    "supporting": [],
    "filters": [
      "rmarkdown/pagebreak.lua"
    ],
    "includes": {
      "include-in-header": [
        "<link href=\"site_libs/htmltools-fill-0.5.8.1/fill.css\" rel=\"stylesheet\" />\n<script src=\"site_libs/htmlwidgets-1.6.4/htmlwidgets.js\"></script>\n<link href=\"site_libs/datatables-css-0.0.0/datatables-crosstalk.css\" rel=\"stylesheet\" />\n<script src=\"site_libs/datatables-binding-0.33/datatables.js\"></script>\n<script src=\"site_libs/jquery-3.6.0/jquery-3.6.0.min.js\"></script>\n<link href=\"site_libs/dt-core-1.13.6/css/jquery.dataTables.min.css\" rel=\"stylesheet\" />\n<link href=\"site_libs/dt-core-1.13.6/css/jquery.dataTables.extra.css\" rel=\"stylesheet\" />\n<script src=\"site_libs/dt-core-1.13.6/js/jquery.dataTables.min.js\"></script>\n<link href=\"site_libs/nouislider-7.0.10/jquery.nouislider.min.css\" rel=\"stylesheet\" />\n<script src=\"site_libs/nouislider-7.0.10/jquery.nouislider.min.js\"></script>\n<link href=\"site_libs/selectize-0.12.0/selectize.bootstrap3.css\" rel=\"stylesheet\" />\n<script src=\"site_libs/selectize-0.12.0/selectize.min.js\"></script>\n<link href=\"site_libs/crosstalk-1.2.1/css/crosstalk.min.css\" rel=\"stylesheet\" />\n<script src=\"site_libs/crosstalk-1.2.1/js/crosstalk.min.js\"></script>\n"
      ]
    },
    "engineDependencies": {},
    "preserve": {},
    "postProcess": true
  }
}